{
  "fingerId": "10",
  "image": "images/10_3.png",
  "editImage": "images/10_3.edit.2019-12-29T051358.561213.png",
  "normImage": "images/10_3.norm.png",
  "binImage": {
    "completed": false,
    "image": "images/10_3.bin.2019-12-23T173800.647882.png"
  },
  "dirImage": {
    "completed": false,
    "angleImage": "",
    "normImage": ""
  },
  "imageSize": {
    "width": 328,
    "height": 364
  },
  "global": {
    "completed": false,
    "fpClass": "right loop",
    "rotation": 0.0
  },
  "regions": {
    "completed": false,
    "regions": [
      {
        "type": "foreground",
        "points": [
          {
            "x": 184.5,
            "y": 40.5
          },
          {
            "x": 172.5,
            "y": 37.5
          },
          {
            "x": 156.5,
            "y": 39.5
          },
          {
            "x": 136.5,
            "y": 38.5
          },
          {
            "x": 100.5,
            "y": 50.5
          },
          {
            "x": 77.5,
            "y": 68.5
          },
          {
            "x": 71.5,
            "y": 77.5
          },
          {
            "x": 57.5,
            "y": 89.5
          },
          {
            "x": 48.5,
            "y": 109.5
          },
          {
            "x": 42.5,
            "y": 118.5
          },
          {
            "x": 34.5,
            "y": 151.5
          },
          {
            "x": 26.5,
            "y": 171.5
          },
          {
            "x": 24.5,
            "y": 190.5
          },
          {
            "x": 24.5,
            "y": 228.5
          },
          {
            "x": 20.5,
            "y": 242.5
          },
          {
            "x": 22.5,
            "y": 302.5
          },
          {
            "x": 27.5,
            "y": 321.5
          },
          {
            "x": 40.5,
            "y": 345.5
          },
          {
            "x": 45.5,
            "y": 352.5
          },
          {
            "x": 57.5,
            "y": 363.5
          },
          {
            "x": 242.5,
            "y": 363.5
          },
          {
            "x": 242.5,
            "y": 360.5
          },
          {
            "x": 250.5,
            "y": 346.5
          },
          {
            "x": 254.5,
            "y": 322.5
          },
          {
            "x": 265.5,
            "y": 299.5
          },
          {
            "x": 268.5,
            "y": 276.5
          },
          {
            "x": 272.5,
            "y": 267.5
          },
          {
            "x": 275.5,
            "y": 251.5
          },
          {
            "x": 275.5,
            "y": 229.5
          },
          {
            "x": 272.5,
            "y": 221.5
          },
          {
            "x": 271.5,
            "y": 172.5
          },
          {
            "x": 267.5,
            "y": 151.5
          },
          {
            "x": 264.5,
            "y": 112.5
          },
          {
            "x": 254.5,
            "y": 97.5
          },
          {
            "x": 241.5,
            "y": 85.5
          },
          {
            "x": 232.5,
            "y": 73.5
          },
          {
            "x": 215.5,
            "y": 56.5
          },
          {
            "x": 204.5,
            "y": 50.5
          },
          {
            "x": 198.5,
            "y": 49.5
          }
        ]
      }
    ]
  },
  "singular": {
    "completed": false,
    "cores": [],
    "deltas": []
  },
  "minutiae": {
    "completed": false,
    "minutiae": []
  }
}