{
  "fingerId": "12",
  "image": "images/12_6.png",
  "normImage": "images/12_6.norm.png",
  "editImage": "images/12_6.edit.2020-04-17T171652.465461.png",
  "binImage": {
    "completed": true,
    "image": "images/12_6.bin.2020-04-17T171653.800342.png"
  },
  "dirImage": {
    "completed": true,
    "angleImage": "images/12_6.dir_angle.2020-09-12T141253.493537.png",
    "normImage": "images/12_6.dir_norm.2020-09-12T141253.493579.png"
  },
  "imageSize": {
    "width": 328,
    "height": 364
  },
  "global": {
    "completed": false,
    "fpClass": "left loop",
    "rotation": 0.0,
    "fpQuality": "high"
  },
  "bbox": {
    "center": {
      "x": 162.0,
      "y": 190.5
    },
    "width": 253.0,
    "height": 346.0,
    "degree": 0.0
  },
  "regions": {
    "completed": true,
    "regions": [
      {
        "type": "foreground",
        "points": [
          {
            "x": 182.5,
            "y": 18.5
          },
          {
            "x": 169.5,
            "y": 18.5
          },
          {
            "x": 156.5,
            "y": 17.5
          },
          {
            "x": 138.5,
            "y": 21.5
          },
          {
            "x": 105.5,
            "y": 31.5
          },
          {
            "x": 94.5,
            "y": 36.5
          },
          {
            "x": 86.5,
            "y": 42.5
          },
          {
            "x": 73.5,
            "y": 56.5
          },
          {
            "x": 65.5,
            "y": 68.5
          },
          {
            "x": 50.5,
            "y": 102.5
          },
          {
            "x": 46.5,
            "y": 123.5
          },
          {
            "x": 42.5,
            "y": 143.5
          },
          {
            "x": 41.5,
            "y": 154.5
          },
          {
            "x": 39.5,
            "y": 169.5
          },
          {
            "x": 37.5,
            "y": 185.5
          },
          {
            "x": 35.5,
            "y": 204.5
          },
          {
            "x": 37.5,
            "y": 216.5
          },
          {
            "x": 38.5,
            "y": 231.5
          },
          {
            "x": 40.5,
            "y": 245.5
          },
          {
            "x": 44.5,
            "y": 261.5
          },
          {
            "x": 46.5,
            "y": 268.5
          },
          {
            "x": 51.5,
            "y": 284.5
          },
          {
            "x": 57.5,
            "y": 303.5
          },
          {
            "x": 60.5,
            "y": 318.5
          },
          {
            "x": 72.5,
            "y": 331.5
          },
          {
            "x": 78.5,
            "y": 339.5
          },
          {
            "x": 83.5,
            "y": 351.5
          },
          {
            "x": 92.5,
            "y": 359.5
          },
          {
            "x": 97.5,
            "y": 363.5
          },
          {
            "x": 195.5,
            "y": 363.5
          },
          {
            "x": 205.5,
            "y": 347.5
          },
          {
            "x": 215.5,
            "y": 343.5
          },
          {
            "x": 232.5,
            "y": 334.5
          },
          {
            "x": 241.5,
            "y": 325.5
          },
          {
            "x": 247.5,
            "y": 319.5
          },
          {
            "x": 252.5,
            "y": 304.5
          },
          {
            "x": 260.5,
            "y": 294.5
          },
          {
            "x": 271.5,
            "y": 277.5
          },
          {
            "x": 277.5,
            "y": 257.5
          },
          {
            "x": 280.5,
            "y": 248.5
          },
          {
            "x": 283.5,
            "y": 231.5
          },
          {
            "x": 287.5,
            "y": 222.5
          },
          {
            "x": 285.5,
            "y": 194.5
          },
          {
            "x": 286.5,
            "y": 177.5
          },
          {
            "x": 288.5,
            "y": 163.5
          },
          {
            "x": 288.5,
            "y": 148.5
          },
          {
            "x": 283.5,
            "y": 126.5
          },
          {
            "x": 278.5,
            "y": 105.5
          },
          {
            "x": 270.5,
            "y": 89.5
          },
          {
            "x": 262.5,
            "y": 72.5
          },
          {
            "x": 253.5,
            "y": 58.5
          },
          {
            "x": 245.5,
            "y": 49.5
          },
          {
            "x": 235.5,
            "y": 42.5
          },
          {
            "x": 224.5,
            "y": 36.5
          },
          {
            "x": 209.5,
            "y": 29.5
          },
          {
            "x": 200.5,
            "y": 24.5
          }
        ]
      }
    ]
  },
  "singular": {
    "completed": false,
    "cores": [],
    "doubleCores": [],
    "deltas": []
  },
  "minutiae": {
    "completed": false,
    "minutiae": []
  }
}