{
  "fingerId": "13",
  "image": "images/13_4.png",
  "editImage": "images/13_4.edit.2020-04-17T192539.768938.png",
  "binImage": {
    "completed": true,
    "image": "images/13_4.bin.2020-04-17T192540.846267.png"
  },
  "dirImage": {
    "completed": true,
    "angleImage": "images/13_4.dir_angle.2020-04-17T192542.538784.png",
    "normImage": "images/13_4.dir_norm.2020-04-17T192542.538826.png"
  },
  "rdImage": {
    "completed": false,
    "image": ""
  },
  "imageSize": {
    "width": 328,
    "height": 364
  },
  "global": {
    "completed": true,
    "fpClass": "whorl",
    "rotation": -1.4797943682027608
  },
  "bbox": {
    "center": {
      "x": 167.1306957045178,
      "y": 182.8491136646087
    },
    "width": 233.903620841819,
    "height": 366.1069890006909,
    "degree": -1.4797943682027608
  },
  "regions": {
    "completed": true,
    "regions": [
      {
        "type": "foreground",
        "points": [
          {
            "x": 137.5,
            "y": 0.5
          },
          {
            "x": 120.5,
            "y": 2.5
          },
          {
            "x": 108.5,
            "y": 5.5
          },
          {
            "x": 99.5,
            "y": 21.5
          },
          {
            "x": 88.5,
            "y": 38.5
          },
          {
            "x": 80.5,
            "y": 54.5
          },
          {
            "x": 75.5,
            "y": 76.5
          },
          {
            "x": 71.5,
            "y": 90.5
          },
          {
            "x": 69.5,
            "y": 102.5
          },
          {
            "x": 71.5,
            "y": 110.5
          },
          {
            "x": 63.5,
            "y": 131.5
          },
          {
            "x": 62.5,
            "y": 148.5
          },
          {
            "x": 59.5,
            "y": 166.5
          },
          {
            "x": 58.5,
            "y": 182.5
          },
          {
            "x": 56.5,
            "y": 207.5
          },
          {
            "x": 54.5,
            "y": 223.5
          },
          {
            "x": 51.5,
            "y": 235.5
          },
          {
            "x": 53.5,
            "y": 260.5
          },
          {
            "x": 55.5,
            "y": 272.5
          },
          {
            "x": 58.5,
            "y": 302.5
          },
          {
            "x": 65.5,
            "y": 325.5
          },
          {
            "x": 70.5,
            "y": 343.5
          },
          {
            "x": 74.5,
            "y": 353.5
          },
          {
            "x": 78.5,
            "y": 363.5
          },
          {
            "x": 262.5,
            "y": 363.5
          },
          {
            "x": 271.5,
            "y": 346.5
          },
          {
            "x": 273.5,
            "y": 328.5
          },
          {
            "x": 277.5,
            "y": 300.5
          },
          {
            "x": 282.5,
            "y": 276.5
          },
          {
            "x": 284.5,
            "y": 247.5
          },
          {
            "x": 283.5,
            "y": 231.5
          },
          {
            "x": 284.5,
            "y": 197.5
          },
          {
            "x": 280.5,
            "y": 183.5
          },
          {
            "x": 275.5,
            "y": 160.5
          },
          {
            "x": 272.5,
            "y": 142.5
          },
          {
            "x": 272.5,
            "y": 119.5
          },
          {
            "x": 270.5,
            "y": 103.5
          },
          {
            "x": 263.5,
            "y": 72.5
          },
          {
            "x": 259.5,
            "y": 56.5
          },
          {
            "x": 249.5,
            "y": 38.5
          },
          {
            "x": 233.5,
            "y": 17.5
          },
          {
            "x": 225.5,
            "y": 12.5
          },
          {
            "x": 214.5,
            "y": 5.5
          },
          {
            "x": 205.5,
            "y": 2.5
          },
          {
            "x": 195.5,
            "y": 0.5
          }
        ]
      }
    ]
  },
  "singular": {
    "completed": false,
    "cores": [],
    "deltas": []
  },
  "minutiae": {
    "completed": false,
    "minutiae": []
  }
}