{
  "fingerId": "35",
  "image": "images/35_5.png",
  "editImage": "images/35_5.edit.2019-12-29T051401.106123.png",
  "binImage": {
    "completed": false,
    "image": "images/35_5.bin.2020-05-08T180331.800946.png"
  },
  "dirImage": {
    "completed": true,
    "angleImage": "images/35_5.dir_angle.2020-07-10T224258.677065.png",
    "normImage": "images/35_5.dir_norm.2020-07-10T224258.677105.png"
  },
  "rdImage": {
    "completed": false,
    "image": ""
  },
  "imageSize": {
    "width": 328,
    "height": 364
  },
  "global": {
    "completed": false,
    "fpClass": "left loop",
    "rotation": 0.0,
    "fpQuality": "low"
  },
  "bbox": {
    "center": {
      "x": 166.0,
      "y": 154.0
    },
    "width": 203.0,
    "height": 307.0,
    "degree": 0.0
  },
  "regions": {
    "completed": true,
    "regions": [
      {
        "type": "foreground",
        "points": [
          {
            "x": 236.5,
            "y": 0.5
          },
          {
            "x": 111.5,
            "y": 0.5
          },
          {
            "x": 97.5,
            "y": 13.5
          },
          {
            "x": 86.5,
            "y": 33.5
          },
          {
            "x": 76.5,
            "y": 56.5
          },
          {
            "x": 68.5,
            "y": 93.5
          },
          {
            "x": 68.5,
            "y": 118.5
          },
          {
            "x": 64.5,
            "y": 143.5
          },
          {
            "x": 65.5,
            "y": 174.5
          },
          {
            "x": 67.5,
            "y": 206.5
          },
          {
            "x": 75.5,
            "y": 225.5
          },
          {
            "x": 81.5,
            "y": 229.5
          },
          {
            "x": 84.5,
            "y": 238.5
          },
          {
            "x": 89.5,
            "y": 259.5
          },
          {
            "x": 94.5,
            "y": 270.5
          },
          {
            "x": 110.5,
            "y": 291.5
          },
          {
            "x": 135.5,
            "y": 298.5
          },
          {
            "x": 145.5,
            "y": 303.5
          },
          {
            "x": 163.5,
            "y": 307.5
          },
          {
            "x": 188.5,
            "y": 291.5
          },
          {
            "x": 202.5,
            "y": 282.5
          },
          {
            "x": 211.5,
            "y": 277.5
          },
          {
            "x": 227.5,
            "y": 257.5
          },
          {
            "x": 239.5,
            "y": 234.5
          },
          {
            "x": 246.5,
            "y": 228.5
          },
          {
            "x": 251.5,
            "y": 199.5
          },
          {
            "x": 252.5,
            "y": 191.5
          },
          {
            "x": 257.5,
            "y": 175.5
          },
          {
            "x": 262.5,
            "y": 163.5
          },
          {
            "x": 265.5,
            "y": 145.5
          },
          {
            "x": 265.5,
            "y": 126.5
          },
          {
            "x": 267.5,
            "y": 117.5
          },
          {
            "x": 267.5,
            "y": 95.5
          },
          {
            "x": 267.5,
            "y": 73.5
          },
          {
            "x": 265.5,
            "y": 61.5
          },
          {
            "x": 260.5,
            "y": 47.5
          },
          {
            "x": 249.5,
            "y": 22.5
          },
          {
            "x": 245.5,
            "y": 8.5
          }
        ]
      },
      {
        "type": "unrecoverable",
        "points": [
          {
            "x": 123.5,
            "y": 281.5
          },
          {
            "x": 139.45557329175068,
            "y": 262.8360144191069
          },
          {
            "x": 151.2793860763514,
            "y": 270.55830369052916
          },
          {
            "x": 151.03806453661946,
            "y": 279.48720066061105
          },
          {
            "x": 135.11084291431115,
            "y": 290.1053484088166
          },
          {
            "x": 133.18121325872016,
            "y": 302.4127469351458
          },
          {
            "x": 112.5,
            "y": 296.5
          }
        ]
      }
    ]
  },
  "singular": {
    "completed": false,
    "cores": [],
    "deltas": []
  },
  "minutiae": {
    "completed": false,
    "minutiae": []
  }
}