{
  "fingerId": "43",
  "image": "images/43_1.png",
  "editImage": "images/43_1.edit.2019-12-29T051401.853862.png",
  "binImage": {
    "completed": false,
    "image": "images/43_1.bin.2019-12-23T173945.881400.png"
  },
  "dirImage": {
    "completed": false,
    "angleImage": "",
    "normImage": ""
  },
  "rdImage": {
    "completed": false,
    "image": ""
  },
  "imageSize": {
    "width": 328,
    "height": 364
  },
  "global": {
    "completed": false,
    "fpClass": "whorl",
    "rotation": 0.0,
    "fpQuality": "very high"
  },
  "bbox": {
    "center": {
      "x": 142.5,
      "y": 129.0
    },
    "width": 232.0,
    "height": 257.0,
    "degree": 0.0
  },
  "regions": {
    "completed": false,
    "regions": [
      {
        "type": "foreground",
        "points": [
          {
            "x": 41.5,
            "y": 0.5
          },
          {
            "x": 36.5,
            "y": 17.5
          },
          {
            "x": 36.5,
            "y": 28.5
          },
          {
            "x": 34.5,
            "y": 33.5
          },
          {
            "x": 29.5,
            "y": 92.5
          },
          {
            "x": 26.5,
            "y": 111.5
          },
          {
            "x": 26.5,
            "y": 126.5
          },
          {
            "x": 40.5,
            "y": 182.5
          },
          {
            "x": 55.5,
            "y": 219.5
          },
          {
            "x": 65.5,
            "y": 234.5
          },
          {
            "x": 76.5,
            "y": 244.5
          },
          {
            "x": 90.5,
            "y": 252.5
          },
          {
            "x": 103.5,
            "y": 257.5
          },
          {
            "x": 119.5,
            "y": 256.5
          },
          {
            "x": 140.5,
            "y": 249.5
          },
          {
            "x": 152.5,
            "y": 248.5
          },
          {
            "x": 163.5,
            "y": 242.5
          },
          {
            "x": 176.5,
            "y": 229.5
          },
          {
            "x": 203.5,
            "y": 191.5
          },
          {
            "x": 211.5,
            "y": 182.5
          },
          {
            "x": 232.5,
            "y": 150.5
          },
          {
            "x": 235.5,
            "y": 138.5
          },
          {
            "x": 240.5,
            "y": 128.5
          },
          {
            "x": 242.5,
            "y": 119.5
          },
          {
            "x": 249.5,
            "y": 102.5
          },
          {
            "x": 257.5,
            "y": 64.5
          },
          {
            "x": 258.5,
            "y": 10.5
          },
          {
            "x": 254.5,
            "y": 3.5
          },
          {
            "x": 254.5,
            "y": 0.5
          }
        ]
      }
    ]
  },
  "singular": {
    "completed": false,
    "cores": [],
    "deltas": []
  },
  "minutiae": {
    "completed": false,
    "minutiae": []
  }
}