{
  "fingerId": "45",
  "image": "images/45_6.png",
  "normImage": "images/45_6.norm.png",
  "editImage": "images/45_6.edit.2020-04-19T184456.724092.png",
  "binImage": {
    "completed": true,
    "image": "images/45_6.bin.2020-04-19T184457.758287.png"
  },
  "dirImage": {
    "completed": true,
    "angleImage": "images/45_6.dir_angle.2020-07-10T225457.729896.png",
    "normImage": "images/45_6.dir_norm.2020-07-10T225457.729941.png"
  },
  "rdImage": {
    "completed": false,
    "image": ""
  },
  "imageSize": {
    "width": 328,
    "height": 364
  },
  "global": {
    "completed": false,
    "fpClass": "right loop",
    "rotation": 20.000000000000924,
    "fpQuality": "high"
  },
  "bbox": {
    "center": {
      "x": 170.6874528161783,
      "y": 170.8788969744283
    },
    "width": 223.57428031160936,
    "height": 400.7961129957729,
    "degree": 20.000000000000924
  },
  "regions": {
    "completed": true,
    "regions": [
      {
        "type": "foreground",
        "points": [
          {
            "x": 301.5,
            "y": 128.5
          },
          {
            "x": 294.5,
            "y": 140.5
          },
          {
            "x": 292.5,
            "y": 156.5
          },
          {
            "x": 287.5,
            "y": 169.5
          },
          {
            "x": 281.5,
            "y": 182.5
          },
          {
            "x": 274.5,
            "y": 212.5
          },
          {
            "x": 267.5,
            "y": 222.5
          },
          {
            "x": 260.5,
            "y": 232.5
          },
          {
            "x": 250.5,
            "y": 249.5
          },
          {
            "x": 244.5,
            "y": 269.5
          },
          {
            "x": 237.5,
            "y": 283.5
          },
          {
            "x": 215.5,
            "y": 312.5
          },
          {
            "x": 200.5,
            "y": 320.5
          },
          {
            "x": 192.5,
            "y": 330.5
          },
          {
            "x": 178.5,
            "y": 336.5
          },
          {
            "x": 169.5,
            "y": 349.5
          },
          {
            "x": 162.5,
            "y": 356.5
          },
          {
            "x": 143.5,
            "y": 359.5
          },
          {
            "x": 130.5,
            "y": 362.5
          },
          {
            "x": 119.5,
            "y": 362.5
          },
          {
            "x": 97.5,
            "y": 357.5
          },
          {
            "x": 87.5,
            "y": 353.5
          },
          {
            "x": 67.5,
            "y": 335.5
          },
          {
            "x": 51.5,
            "y": 319.5
          },
          {
            "x": 44.5,
            "y": 308.5
          },
          {
            "x": 40.5,
            "y": 293.5
          },
          {
            "x": 38.5,
            "y": 239.5
          },
          {
            "x": 39.5,
            "y": 225.5
          },
          {
            "x": 45.5,
            "y": 189.5
          },
          {
            "x": 51.5,
            "y": 171.5
          },
          {
            "x": 59.5,
            "y": 154.5
          },
          {
            "x": 70.5,
            "y": 122.5
          },
          {
            "x": 77.5,
            "y": 103.5
          },
          {
            "x": 82.5,
            "y": 91.5
          },
          {
            "x": 88.5,
            "y": 75.5
          },
          {
            "x": 94.5,
            "y": 65.5
          },
          {
            "x": 95.5,
            "y": 55.5
          },
          {
            "x": 100.5,
            "y": 42.5
          },
          {
            "x": 109.5,
            "y": 28.5
          },
          {
            "x": 123.5,
            "y": 14.5
          },
          {
            "x": 128.5,
            "y": 3.5
          },
          {
            "x": 141.5,
            "y": 2.5
          },
          {
            "x": 150.5,
            "y": 0.5
          },
          {
            "x": 278.5,
            "y": 0.5
          },
          {
            "x": 288.5,
            "y": 0.5
          },
          {
            "x": 289.5,
            "y": 15.5
          },
          {
            "x": 297.5,
            "y": 86.5
          }
        ]
      }
    ]
  },
  "singular": {
    "completed": false,
    "cores": [],
    "doubleCores": [],
    "deltas": []
  },
  "minutiae": {
    "completed": false,
    "minutiae": []
  }
}