{
  "fingerId": "66",
  "image": "images/66_1.png",
  "normImage": "images/66_1.norm.png",
  "editImage": "images/66_1.edit.2019-12-29T051404.188985.png",
  "binImage": {
    "completed": false,
    "image": "images/66_1.bin.2019-12-23T174058.499978.png"
  },
  "dirImage": {
    "completed": false,
    "angleImage": "images/66_1.dir_angle.2020-09-02T114713.318396.png",
    "normImage": "images/66_1.dir_norm.2020-09-02T114713.318417.png"
  },
  "imageSize": {
    "width": 328,
    "height": 364
  },
  "global": {
    "completed": false,
    "fpClass": "right loop",
    "rotation": 0.0,
    "fpQuality": "medium"
  },
  "bbox": {
    "center": {
      "x": 190.0,
      "y": 182.0
    },
    "width": 233.0,
    "height": 363.0,
    "degree": 0.0
  },
  "regions": {
    "completed": false,
    "regions": [
      {
        "type": "foreground",
        "points": [
          {
            "x": 84.5,
            "y": 0.5
          },
          {
            "x": 77.5,
            "y": 18.5
          },
          {
            "x": 76.5,
            "y": 39.5
          },
          {
            "x": 73.5,
            "y": 59.5
          },
          {
            "x": 73.5,
            "y": 108.5
          },
          {
            "x": 75.5,
            "y": 123.5
          },
          {
            "x": 80.5,
            "y": 138.5
          },
          {
            "x": 83.5,
            "y": 168.5
          },
          {
            "x": 86.5,
            "y": 178.5
          },
          {
            "x": 87.5,
            "y": 190.5
          },
          {
            "x": 99.5,
            "y": 230.5
          },
          {
            "x": 127.5,
            "y": 290.5
          },
          {
            "x": 129.5,
            "y": 298.5
          },
          {
            "x": 133.5,
            "y": 306.5
          },
          {
            "x": 139.5,
            "y": 313.5
          },
          {
            "x": 166.5,
            "y": 336.5
          },
          {
            "x": 178.5,
            "y": 342.5
          },
          {
            "x": 191.5,
            "y": 352.5
          },
          {
            "x": 204.5,
            "y": 357.5
          },
          {
            "x": 223.5,
            "y": 359.5
          },
          {
            "x": 227.5,
            "y": 361.5
          },
          {
            "x": 227.5,
            "y": 363.5
          },
          {
            "x": 259.5,
            "y": 363.5
          },
          {
            "x": 260.5,
            "y": 360.5
          },
          {
            "x": 278.5,
            "y": 343.5
          },
          {
            "x": 289.5,
            "y": 320.5
          },
          {
            "x": 293.5,
            "y": 303.5
          },
          {
            "x": 293.5,
            "y": 291.5
          },
          {
            "x": 298.5,
            "y": 264.5
          },
          {
            "x": 298.5,
            "y": 252.5
          },
          {
            "x": 304.5,
            "y": 236.5
          },
          {
            "x": 306.5,
            "y": 225.5
          },
          {
            "x": 306.5,
            "y": 177.5
          },
          {
            "x": 303.5,
            "y": 156.5
          },
          {
            "x": 303.5,
            "y": 142.5
          },
          {
            "x": 301.5,
            "y": 134.5
          },
          {
            "x": 301.5,
            "y": 121.5
          },
          {
            "x": 297.5,
            "y": 96.5
          },
          {
            "x": 297.5,
            "y": 85.5
          },
          {
            "x": 294.5,
            "y": 71.5
          },
          {
            "x": 293.5,
            "y": 34.5
          },
          {
            "x": 286.5,
            "y": 5.5
          },
          {
            "x": 286.5,
            "y": 0.5
          }
        ]
      }
    ]
  },
  "singular": {
    "completed": false,
    "cores": [],
    "doubleCores": [],
    "deltas": []
  },
  "minutiae": {
    "completed": false,
    "minutiae": []
  }
}