{
  "fingerId": "69",
  "image": "images/69_6.png",
  "normImage": "images/69_6.norm.png",
  "editImage": "images/69_6.edit.png",
  "binImage": {
    "completed": false,
    "image": ""
  },
  "dirImage": {
    "completed": true,
    "angleImage": "images/69_6.dir_angle.2020-09-12T141555.983317.png",
    "normImage": "images/69_6.dir_norm.2020-09-12T141555.983356.png"
  },
  "imageSize": {
    "width": 328,
    "height": 364
  },
  "global": {
    "completed": false,
    "fpClass": "right loop",
    "rotation": 6.500000000000732,
    "fpQuality": "high"
  },
  "bbox": {
    "center": {
      "x": 135.9698136813135,
      "y": 183.87649824039542
    },
    "width": 227.88064671864748,
    "height": 375.835814255502,
    "degree": 6.500000000000732
  },
  "regions": {
    "completed": true,
    "regions": [
      {
        "type": "foreground",
        "points": [
          {
            "x": 249.5,
            "y": 187.5
          },
          {
            "x": 247.5,
            "y": 211.5
          },
          {
            "x": 240.5,
            "y": 266.5
          },
          {
            "x": 237.5,
            "y": 285.5
          },
          {
            "x": 231.5,
            "y": 289.5
          },
          {
            "x": 235.5,
            "y": 315.5
          },
          {
            "x": 227.5,
            "y": 323.5
          },
          {
            "x": 219.5,
            "y": 336.5
          },
          {
            "x": 210.5,
            "y": 356.5
          },
          {
            "x": 206.5,
            "y": 361.5
          },
          {
            "x": 202.5,
            "y": 363.5
          },
          {
            "x": 52.5,
            "y": 363.5
          },
          {
            "x": 45.5,
            "y": 357.5
          },
          {
            "x": 42.5,
            "y": 352.5
          },
          {
            "x": 32.5,
            "y": 324.5
          },
          {
            "x": 23.5,
            "y": 289.5
          },
          {
            "x": 18.5,
            "y": 252.5
          },
          {
            "x": 17.5,
            "y": 219.5
          },
          {
            "x": 23.5,
            "y": 164.5
          },
          {
            "x": 53.5,
            "y": 83.5
          },
          {
            "x": 73.5,
            "y": 61.5
          },
          {
            "x": 87.5,
            "y": 45.5
          },
          {
            "x": 91.5,
            "y": 30.5
          },
          {
            "x": 95.5,
            "y": 23.5
          },
          {
            "x": 102.5,
            "y": 16.5
          },
          {
            "x": 124.5,
            "y": 2.5
          },
          {
            "x": 137.5,
            "y": 0.5
          },
          {
            "x": 186.5,
            "y": 0.5
          },
          {
            "x": 227.5,
            "y": 42.5
          },
          {
            "x": 232.5,
            "y": 48.5
          },
          {
            "x": 234.5,
            "y": 53.5
          },
          {
            "x": 235.5,
            "y": 71.5
          },
          {
            "x": 231.5,
            "y": 78.5
          },
          {
            "x": 240.5,
            "y": 96.5
          },
          {
            "x": 245.5,
            "y": 112.5
          },
          {
            "x": 247.5,
            "y": 133.5
          }
        ]
      }
    ]
  },
  "singular": {
    "completed": false,
    "cores": [],
    "doubleCores": [],
    "deltas": []
  },
  "minutiae": {
    "completed": false,
    "minutiae": []
  }
}