{
  "fingerId": "80",
  "image": "images/80_8.png",
  "normImage": "images/80_8.norm.png",
  "editImage": "images/80_8.edit.png",
  "binImage": {
    "completed": false,
    "image": "images/80_8.bin.2020-01-16T220636.149617.png"
  },
  "dirImage": {
    "completed": true,
    "angleImage": "images/80_8.dir_angle.2020-09-12T141631.673677.png",
    "normImage": "images/80_8.dir_norm.2020-09-12T141631.673720.png"
  },
  "imageSize": {
    "width": 328,
    "height": 364
  },
  "global": {
    "completed": false,
    "fpClass": "double loop",
    "rotation": 6.000000000000725,
    "fpQuality": "low"
  },
  "bbox": {
    "center": {
      "x": 158.06638107170068,
      "y": 183.92588410786405
    },
    "width": 274.72383887627973,
    "height": 384.47658652794837,
    "degree": 6.000000000000725
  },
  "regions": {
    "completed": true,
    "regions": [
      {
        "type": "foreground",
        "points": [
          {
            "x": 296.5,
            "y": 139.5
          },
          {
            "x": 295.5,
            "y": 183.5
          },
          {
            "x": 291.5,
            "y": 228.5
          },
          {
            "x": 280.5,
            "y": 290.5
          },
          {
            "x": 260.5,
            "y": 342.5
          },
          {
            "x": 246.5,
            "y": 363.5
          },
          {
            "x": 27.5,
            "y": 363.5
          },
          {
            "x": 19.5,
            "y": 345.5
          },
          {
            "x": 10.5,
            "y": 295.5
          },
          {
            "x": 9.5,
            "y": 283.5
          },
          {
            "x": 32.5,
            "y": 64.5
          },
          {
            "x": 36.5,
            "y": 27.5
          },
          {
            "x": 42.5,
            "y": 1.5
          },
          {
            "x": 261.5,
            "y": 1.5
          },
          {
            "x": 274.5,
            "y": 22.5
          },
          {
            "x": 286.5,
            "y": 56.5
          }
        ]
      }
    ]
  },
  "singular": {
    "completed": false,
    "cores": [],
    "doubleCores": [],
    "deltas": []
  },
  "minutiae": {
    "completed": false,
    "minutiae": []
  }
}