{
  "fingerId": "8",
  "image": "images/8_1.png",
  "editImage": "images/8_1.edit.2019-12-29T051358.333784.png",
  "normImage": "images/8_1.norm.png",
  "binImage": {
    "completed": false,
    "image": "images/8_1.bin.2019-12-23T173751.500956.png"
  },
  "dirImage": {
    "completed": false,
    "angleImage": "",
    "normImage": ""
  },
  "imageSize": {
    "width": 328,
    "height": 364
  },
  "global": {
    "completed": false,
    "fpClass": "left loop",
    "rotation": 0.0
  },
  "regions": {
    "completed": false,
    "regions": [
      {
        "type": "foreground",
        "points": [
          {
            "x": 40.5,
            "y": 0.5
          },
          {
            "x": 34.5,
            "y": 30.5
          },
          {
            "x": 32.5,
            "y": 72.5
          },
          {
            "x": 28.5,
            "y": 92.5
          },
          {
            "x": 27.5,
            "y": 138.5
          },
          {
            "x": 23.5,
            "y": 152.5
          },
          {
            "x": 23.5,
            "y": 163.5
          },
          {
            "x": 20.5,
            "y": 173.5
          },
          {
            "x": 18.5,
            "y": 173.5
          },
          {
            "x": 18.5,
            "y": 312.5
          },
          {
            "x": 22.5,
            "y": 313.5
          },
          {
            "x": 24.5,
            "y": 321.5
          },
          {
            "x": 29.5,
            "y": 329.5
          },
          {
            "x": 34.5,
            "y": 354.5
          },
          {
            "x": 38.5,
            "y": 358.5
          },
          {
            "x": 39.5,
            "y": 363.5
          },
          {
            "x": 224.5,
            "y": 363.5
          },
          {
            "x": 228.5,
            "y": 358.5
          },
          {
            "x": 238.5,
            "y": 354.5
          },
          {
            "x": 243.5,
            "y": 347.5
          },
          {
            "x": 243.5,
            "y": 342.5
          },
          {
            "x": 249.5,
            "y": 328.5
          },
          {
            "x": 250.5,
            "y": 316.5
          },
          {
            "x": 253.5,
            "y": 309.5
          },
          {
            "x": 256.5,
            "y": 306.5
          },
          {
            "x": 263.5,
            "y": 278.5
          },
          {
            "x": 267.5,
            "y": 270.5
          },
          {
            "x": 269.5,
            "y": 250.5
          },
          {
            "x": 274.5,
            "y": 235.5
          },
          {
            "x": 276.5,
            "y": 221.5
          },
          {
            "x": 282.5,
            "y": 200.5
          },
          {
            "x": 286.5,
            "y": 174.5
          },
          {
            "x": 284.5,
            "y": 157.5
          },
          {
            "x": 287.5,
            "y": 147.5
          },
          {
            "x": 286.5,
            "y": 100.5
          },
          {
            "x": 282.5,
            "y": 89.5
          },
          {
            "x": 282.5,
            "y": 82.5
          },
          {
            "x": 272.5,
            "y": 46.5
          },
          {
            "x": 267.5,
            "y": 34.5
          },
          {
            "x": 266.5,
            "y": 26.5
          },
          {
            "x": 258.5,
            "y": 13.5
          },
          {
            "x": 249.5,
            "y": 3.5
          },
          {
            "x": 249.5,
            "y": 0.5
          }
        ]
      }
    ]
  },
  "singular": {
    "completed": false,
    "cores": [],
    "deltas": []
  },
  "minutiae": {
    "completed": false,
    "minutiae": []
  }
}